ducktools/pythonfinder/__init__.py
ducktools/pythonfinder/__main__.py
ducktools/pythonfinder/_version.py
ducktools/pythonfinder/details_script.py
ducktools/pythonfinder/package_list_script.py
ducktools/pythonfinder/py.typed
ducktools/pythonfinder/pythonorg_search.py
ducktools/pythonfinder/shared.py
ducktools/pythonfinder/venv.py
ducktools/pythonfinder/darwin/__init__.py
ducktools/pythonfinder/linux/__init__.py
ducktools/pythonfinder/linux/pyenv_search.py
ducktools/pythonfinder/win32/__init__.py
ducktools/pythonfinder/win32/pyenv_search.py
ducktools/pythonfinder/win32/registry_search.py
ducktools_pythonfinder-0.10.1.dist-info/licenses/LICENSE
ducktools_pythonfinder-0.10.1.dist-info/METADATA
ducktools_pythonfinder-0.10.1.dist-info/WHEEL
ducktools_pythonfinder-0.10.1.dist-info/entry_points.txt
ducktools_pythonfinder-0.10.1.dist-info/top_level.txt
ducktools_pythonfinder-0.10.1.dist-info/RECORD
