Metadata-Version: 2.4
Name: ducktools-pythonfinder
Version: 0.10.1
Summary: Cross platform tool to find available python installations
Author: David C Ellis
Project-URL: Homepage, https://github.com/davidcellis/ducktools-pythonfinder
Classifier: Development Status :: 3 - Alpha
Classifier: Programming Language :: Python :: 3.10
Classifier: Programming Language :: Python :: 3.11
Classifier: Programming Language :: Python :: 3.12
Classifier: Programming Language :: Python :: 3.13
Classifier: License :: OSI Approved :: MIT License
Classifier: Operating System :: MacOS
Classifier: Operating System :: Microsoft :: Windows :: Windows 10
Classifier: Operating System :: POSIX :: Linux
Requires-Python: >=3.10
License-File: LICENSE
Requires-Dist: ducktools-lazyimporter>=0.7.3
Requires-Dist: ducktools-classbuilder>=0.9.1
Requires-Dist: packaging>=24.2
Dynamic: license-file
